README.md
setup.cfg
setup.py
distributions/Binomialdistribution.py
distributions/Gaussiandistribution.py
distributions/Generaldistribution.py
distributions/__init__.py
stats_by_44.egg-info/PKG-INFO
stats_by_44.egg-info/SOURCES.txt
stats_by_44.egg-info/dependency_links.txt
stats_by_44.egg-info/not-zip-safe
stats_by_44.egg-info/top_level.txt