Metadata-Version: 1.0
Name: stats-by-44
Version: 0.0
Summary: Gaussian & Binomail distributions
Home-page: UNKNOWN
Author: bobama
Author-email: bobbmare@gmail.com
License: UNKNOWN
Platform: UNKNOWN
